{
  "wav": "utt_0028.wav",
  "sample_rate": 16000,
  "fps": 30,
  "duration": 6.717625,
  "type_map": [
    "happy",
    "sad",
    "angry",
    "fear",
    "calm",
    "confused"
  ],
  "switch_params": {
    "thr_on": 0.78,
    "thr_off": 0.6,
    "confirm_win": 3,
    "min_gap": 5
  },
  "switch_frames": [
    46,
    61,
    91,
    125,
    153,
    176
  ],
  "switch_times": [
    1.5333333333333334,
    2.033333333333333,
    3.033333333333333,
    4.166666666666667,
    5.1,
    5.866666666666666
  ],
  "frames": [
    {
      "i": 0,
      "t": 0.0,
      "type_id": 3,
      "level_id": 2,
      "boundary_p": 0.0010019963374361396
    },
    {
      "i": 1,
      "t": 0.03333333333333333,
      "type_id": 3,
      "level_id": 5,
      "boundary_p": 0.0012835224624723196
    },
    {
      "i": 2,
      "t": 0.06666666666666667,
      "type_id": 3,
      "level_id": 2,
      "boundary_p": 0.00461778836324811
    },
    {
      "i": 3,
      "t": 0.1,
      "type_id": 0,
      "level_id": 5,
      "boundary_p": 0.009391583502292633
    },
    {
      "i": 4,
      "t": 0.13333333333333333,
      "type_id": 0,
      "level_id": 5,
      "boundary_p": 0.06029617041349411
    },
    {
      "i": 5,
      "t": 0.16666666666666666,
      "type_id": 3,
      "level_id": 3,
      "boundary_p": 0.07611656188964844
    },
    {
      "i": 6,
      "t": 0.2,
      "type_id": 0,
      "level_id": 2,
      "boundary_p": 0.01976676471531391
    },
    {
      "i": 7,
      "t": 0.23333333333333334,
      "type_id": 1,
      "level_id": 5,
      "boundary_p": 0.0006913688848726451
    },
    {
      "i": 8,
      "t": 0.26666666666666666,
      "type_id": 1,
      "level_id": 5,
      "boundary_p": 0.017132258042693138
    },
    {
      "i": 9,
      "t": 0.3,
      "type_id": 0,
      "level_id": 5,
      "boundary_p": 0.0037034261040389538
    },
    {
      "i": 10,
      "t": 0.3333333333333333,
      "type_id": 0,
      "level_id": 3,
      "boundary_p": 0.0017390737775713205
    },
    {
      "i": 11,
      "t": 0.36666666666666664,
      "type_id": 3,
      "level_id": 3,
      "boundary_p": 0.0008147567277774215
    },
    {
      "i": 12,
      "t": 0.4,
      "type_id": 0,
      "level_id": 5,
      "boundary_p": 0.0011056535877287388
    },
    {
      "i": 13,
      "t": 0.43333333333333335,
      "type_id": 3,
      "level_id": 3,
      "boundary_p": 0.0010254346998408437
    },
    {
      "i": 14,
      "t": 0.4666666666666667,
      "type_id": 1,
      "level_id": 3,
      "boundary_p": 0.0012688719434663653
    },
    {
      "i": 15,
      "t": 0.5,
      "type_id": 0,
      "level_id": 5,
      "boundary_p": 0.0003630545979831368
    },
    {
      "i": 16,
      "t": 0.5333333333333333,
      "type_id": 1,
      "level_id": 2,
      "boundary_p": 4.7391567932209e-05
    },
    {
      "i": 17,
      "t": 0.5666666666666667,
      "type_id": 1,
      "level_id": 2,
      "boundary_p": 0.00021598378953058273
    },
    {
      "i": 18,
      "t": 0.6,
      "type_id": 0,
      "level_id": 2,
      "boundary_p": 0.004557562991976738
    },
    {
      "i": 19,
      "t": 0.6333333333333333,
      "type_id": 0,
      "level_id": 2,
      "boundary_p": 0.0050578429363667965
    },
    {
      "i": 20,
      "t": 0.6666666666666666,
      "type_id": 0,
      "level_id": 3,
      "boundary_p": 0.28664565086364746
    },
    {
      "i": 21,
      "t": 0.7,
      "type_id": 1,
      "level_id": 3,
      "boundary_p": 0.3440018594264984
    },
    {
      "i": 22,
      "t": 0.7333333333333333,
      "type_id": 1,
      "level_id": 3,
      "boundary_p": 0.7621098160743713
    },
    {
      "i": 23,
      "t": 0.7666666666666667,
      "type_id": 0,
      "level_id": 3,
      "boundary_p": 0.10562549531459808
    },
    {
      "i": 24,
      "t": 0.8,
      "type_id": 1,
      "level_id": 3,
      "boundary_p": 0.08454885333776474
    },
    {
      "i": 25,
      "t": 0.8333333333333334,
      "type_id": 1,
      "level_id": 3,
      "boundary_p": 0.009553305804729462
    },
    {
      "i": 26,
      "t": 0.8666666666666667,
      "type_id": 1,
      "level_id": 3,
      "boundary_p": 0.002548330696299672
    },
    {
      "i": 27,
      "t": 0.9,
      "type_id": 1,
      "level_id": 3,
      "boundary_p": 0.0018249924760311842
    },
    {
      "i": 28,
      "t": 0.9333333333333333,
      "type_id": 1,
      "level_id": 3,
      "boundary_p": 0.004554286599159241
    },
    {
      "i": 29,
      "t": 0.9666666666666667,
      "type_id": 1,
      "level_id": 3,
      "boundary_p": 0.01466003805398941
    },
    {
      "i": 30,
      "t": 1.0,
      "type_id": 1,
      "level_id": 3,
      "boundary_p": 0.0029679336585104465
    },
    {
      "i": 31,
      "t": 1.0333333333333334,
      "type_id": 0,
      "level_id": 3,
      "boundary_p": 0.0014163899468258023
    },
    {
      "i": 32,
      "t": 1.0666666666666667,
      "type_id": 0,
      "level_id": 3,
      "boundary_p": 0.030502311885356903
    },
    {
      "i": 33,
      "t": 1.1,
      "type_id": 0,
      "level_id": 3,
      "boundary_p": 0.02285006269812584
    },
    {
      "i": 34,
      "t": 1.1333333333333333,
      "type_id": 0,
      "level_id": 3,
      "boundary_p": 0.025149598717689514
    },
    {
      "i": 35,
      "t": 1.1666666666666667,
      "type_id": 3,
      "level_id": 3,
      "boundary_p": 0.011233867146074772
    },
    {
      "i": 36,
      "t": 1.2,
      "type_id": 1,
      "level_id": 3,
      "boundary_p": 0.013516847975552082
    },
    {
      "i": 37,
      "t": 1.2333333333333334,
      "type_id": 1,
      "level_id": 3,
      "boundary_p": 0.011974658817052841
    },
    {
      "i": 38,
      "t": 1.2666666666666666,
      "type_id": 0,
      "level_id": 3,
      "boundary_p": 0.046633280813694
    },
    {
      "i": 39,
      "t": 1.3,
      "type_id": 0,
      "level_id": 3,
      "boundary_p": 0.22147274017333984
    },
    {
      "i": 40,
      "t": 1.3333333333333333,
      "type_id": 0,
      "level_id": 2,
      "boundary_p": 0.2537982761859894
    },
    {
      "i": 41,
      "t": 1.3666666666666667,
      "type_id": 0,
      "level_id": 3,
      "boundary_p": 0.1391391158103943
    },
    {
      "i": 42,
      "t": 1.4,
      "type_id": 0,
      "level_id": 3,
      "boundary_p": 0.11598540097475052
    },
    {
      "i": 43,
      "t": 1.4333333333333333,
      "type_id": 0,
      "level_id": 3,
      "boundary_p": 0.15313506126403809
    },
    {
      "i": 44,
      "t": 1.4666666666666666,
      "type_id": 0,
      "level_id": 3,
      "boundary_p": 0.7382225394248962
    },
    {
      "i": 45,
      "t": 1.5,
      "type_id": 0,
      "level_id": 3,
      "boundary_p": 0.819071352481842
    },
    {
      "i": 46,
      "t": 1.5333333333333334,
      "type_id": 0,
      "level_id": 3,
      "boundary_p": 0.8250499367713928
    },
    {
      "i": 47,
      "t": 1.5666666666666667,
      "type_id": 0,
      "level_id": 3,
      "boundary_p": 0.5293711423873901
    },
    {
      "i": 48,
      "t": 1.6,
      "type_id": 0,
      "level_id": 3,
      "boundary_p": 0.34791409969329834
    },
    {
      "i": 49,
      "t": 1.6333333333333333,
      "type_id": 0,
      "level_id": 3,
      "boundary_p": 0.08028224855661392
    },
    {
      "i": 50,
      "t": 1.6666666666666667,
      "type_id": 0,
      "level_id": 3,
      "boundary_p": 0.04603533819317818
    },
    {
      "i": 51,
      "t": 1.7,
      "type_id": 0,
      "level_id": 3,
      "boundary_p": 0.011749975383281708
    },
    {
      "i": 52,
      "t": 1.7333333333333334,
      "type_id": 0,
      "level_id": 3,
      "boundary_p": 0.002257314510643482
    },
    {
      "i": 53,
      "t": 1.7666666666666666,
      "type_id": 1,
      "level_id": 3,
      "boundary_p": 0.0004504137032199651
    },
    {
      "i": 54,
      "t": 1.8,
      "type_id": 0,
      "level_id": 3,
      "boundary_p": 0.00012095974670955911
    },
    {
      "i": 55,
      "t": 1.8333333333333333,
      "type_id": 0,
      "level_id": 3,
      "boundary_p": 0.0013692198554053903
    },
    {
      "i": 56,
      "t": 1.8666666666666667,
      "type_id": 1,
      "level_id": 2,
      "boundary_p": 0.002934308722615242
    },
    {
      "i": 57,
      "t": 1.9,
      "type_id": 1,
      "level_id": 2,
      "boundary_p": 0.004062984604388475
    },
    {
      "i": 58,
      "t": 1.9333333333333333,
      "type_id": 0,
      "level_id": 2,
      "boundary_p": 0.013877546414732933
    },
    {
      "i": 59,
      "t": 1.9666666666666666,
      "type_id": 0,
      "level_id": 3,
      "boundary_p": 0.005149348638951778
    },
    {
      "i": 60,
      "t": 2.0,
      "type_id": 0,
      "level_id": 2,
      "boundary_p": 0.0024056595284491777
    },
    {
      "i": 61,
      "t": 2.033333333333333,
      "type_id": 0,
      "level_id": 3,
      "boundary_p": 0.8459100127220154
    },
    {
      "i": 62,
      "t": 2.066666666666667,
      "type_id": 0,
      "level_id": 3,
      "boundary_p": 0.47991490364074707
    },
    {
      "i": 63,
      "t": 2.1,
      "type_id": 0,
      "level_id": 2,
      "boundary_p": 0.02897808700799942
    },
    {
      "i": 64,
      "t": 2.1333333333333333,
      "type_id": 0,
      "level_id": 3,
      "boundary_p": 0.004622147884219885
    },
    {
      "i": 65,
      "t": 2.1666666666666665,
      "type_id": 1,
      "level_id": 4,
      "boundary_p": 0.018121734261512756
    },
    {
      "i": 66,
      "t": 2.2,
      "type_id": 0,
      "level_id": 4,
      "boundary_p": 0.0030732813756912947
    },
    {
      "i": 67,
      "t": 2.2333333333333334,
      "type_id": 0,
      "level_id": 3,
      "boundary_p": 0.012744852341711521
    },
    {
      "i": 68,
      "t": 2.2666666666666666,
      "type_id": 0,
      "level_id": 4,
      "boundary_p": 0.031965892761945724
    },
    {
      "i": 69,
      "t": 2.3,
      "type_id": 0,
      "level_id": 2,
      "boundary_p": 0.014317561872303486
    },
    {
      "i": 70,
      "t": 2.3333333333333335,
      "type_id": 0,
      "level_id": 2,
      "boundary_p": 0.07654187083244324
    },
    {
      "i": 71,
      "t": 2.3666666666666667,
      "type_id": 0,
      "level_id": 4,
      "boundary_p": 0.0105298962444067
    },
    {
      "i": 72,
      "t": 2.4,
      "type_id": 0,
      "level_id": 4,
      "boundary_p": 0.006141618825495243
    },
    {
      "i": 73,
      "t": 2.433333333333333,
      "type_id": 0,
      "level_id": 4,
      "boundary_p": 0.0409289114177227
    },
    {
      "i": 74,
      "t": 2.466666666666667,
      "type_id": 0,
      "level_id": 0,
      "boundary_p": 0.0033184385392814875
    },
    {
      "i": 75,
      "t": 2.5,
      "type_id": 0,
      "level_id": 2,
      "boundary_p": 0.00116619688924402
    },
    {
      "i": 76,
      "t": 2.533333333333333,
      "type_id": 0,
      "level_id": 2,
      "boundary_p": 0.0005959989503026009
    },
    {
      "i": 77,
      "t": 2.566666666666667,
      "type_id": 0,
      "level_id": 4,
      "boundary_p": 0.01190181914716959
    },
    {
      "i": 78,
      "t": 2.6,
      "type_id": 0,
      "level_id": 4,
      "boundary_p": 0.0022616370115429163
    },
    {
      "i": 79,
      "t": 2.6333333333333333,
      "type_id": 0,
      "level_id": 4,
      "boundary_p": 0.00022645530407316983
    },
    {
      "i": 80,
      "t": 2.6666666666666665,
      "type_id": 0,
      "level_id": 4,
      "boundary_p": 0.017857901751995087
    },
    {
      "i": 81,
      "t": 2.7,
      "type_id": 0,
      "level_id": 3,
      "boundary_p": 0.005003666039556265
    },
    {
      "i": 82,
      "t": 2.7333333333333334,
      "type_id": 0,
      "level_id": 4,
      "boundary_p": 0.01531982235610485
    },
    {
      "i": 83,
      "t": 2.7666666666666666,
      "type_id": 3,
      "level_id": 3,
      "boundary_p": 0.004922239575535059
    },
    {
      "i": 84,
      "t": 2.8,
      "type_id": 0,
      "level_id": 2,
      "boundary_p": 0.04585958644747734
    },
    {
      "i": 85,
      "t": 2.8333333333333335,
      "type_id": 0,
      "level_id": 2,
      "boundary_p": 0.07507487386465073
    },
    {
      "i": 86,
      "t": 2.8666666666666667,
      "type_id": 0,
      "level_id": 3,
      "boundary_p": 0.17566923797130585
    },
    {
      "i": 87,
      "t": 2.9,
      "type_id": 0,
      "level_id": 3,
      "boundary_p": 0.124766506254673
    },
    {
      "i": 88,
      "t": 2.933333333333333,
      "type_id": 0,
      "level_id": 2,
      "boundary_p": 0.1565835177898407
    },
    {
      "i": 89,
      "t": 2.966666666666667,
      "type_id": 0,
      "level_id": 2,
      "boundary_p": 0.4683806300163269
    },
    {
      "i": 90,
      "t": 3.0,
      "type_id": 0,
      "level_id": 2,
      "boundary_p": 0.6301316618919373
    },
    {
      "i": 91,
      "t": 3.033333333333333,
      "type_id": 0,
      "level_id": 2,
      "boundary_p": 0.975807785987854
    },
    {
      "i": 92,
      "t": 3.066666666666667,
      "type_id": 0,
      "level_id": 3,
      "boundary_p": 0.8224550485610962
    },
    {
      "i": 93,
      "t": 3.1,
      "type_id": 0,
      "level_id": 4,
      "boundary_p": 0.319231241941452
    },
    {
      "i": 94,
      "t": 3.1333333333333333,
      "type_id": 0,
      "level_id": 3,
      "boundary_p": 0.03211401402950287
    },
    {
      "i": 95,
      "t": 3.1666666666666665,
      "type_id": 0,
      "level_id": 4,
      "boundary_p": 0.0038423703517764807
    },
    {
      "i": 96,
      "t": 3.2,
      "type_id": 0,
      "level_id": 4,
      "boundary_p": 0.0013008186360821128
    },
    {
      "i": 97,
      "t": 3.2333333333333334,
      "type_id": 0,
      "level_id": 3,
      "boundary_p": 0.00512999203056097
    },
    {
      "i": 98,
      "t": 3.2666666666666666,
      "type_id": 0,
      "level_id": 2,
      "boundary_p": 0.002362113678827882
    },
    {
      "i": 99,
      "t": 3.3,
      "type_id": 0,
      "level_id": 0,
      "boundary_p": 0.003273828886449337
    },
    {
      "i": 100,
      "t": 3.3333333333333335,
      "type_id": 0,
      "level_id": 4,
      "boundary_p": 0.004668768495321274
    },
    {
      "i": 101,
      "t": 3.3666666666666667,
      "type_id": 0,
      "level_id": 4,
      "boundary_p": 0.00026712933322414756
    },
    {
      "i": 102,
      "t": 3.4,
      "type_id": 0,
      "level_id": 4,
      "boundary_p": 0.002875882899388671
    },
    {
      "i": 103,
      "t": 3.433333333333333,
      "type_id": 0,
      "level_id": 4,
      "boundary_p": 0.0018264070386067033
    },
    {
      "i": 104,
      "t": 3.466666666666667,
      "type_id": 0,
      "level_id": 4,
      "boundary_p": 0.02785603702068329
    },
    {
      "i": 105,
      "t": 3.5,
      "type_id": 0,
      "level_id": 3,
      "boundary_p": 0.0006325108115561306
    },
    {
      "i": 106,
      "t": 3.533333333333333,
      "type_id": 0,
      "level_id": 3,
      "boundary_p": 0.00034778183908201754
    },
    {
      "i": 107,
      "t": 3.566666666666667,
      "type_id": 0,
      "level_id": 4,
      "boundary_p": 0.0002063256542896852
    },
    {
      "i": 108,
      "t": 3.6,
      "type_id": 0,
      "level_id": 3,
      "boundary_p": 0.01242538820952177
    },
    {
      "i": 109,
      "t": 3.6333333333333333,
      "type_id": 0,
      "level_id": 2,
      "boundary_p": 0.08703438192605972
    },
    {
      "i": 110,
      "t": 3.6666666666666665,
      "type_id": 0,
      "level_id": 3,
      "boundary_p": 0.23518837988376617
    },
    {
      "i": 111,
      "t": 3.7,
      "type_id": 0,
      "level_id": 4,
      "boundary_p": 0.10582860559225082
    },
    {
      "i": 112,
      "t": 3.7333333333333334,
      "type_id": 0,
      "level_id": 4,
      "boundary_p": 0.018725411966443062
    },
    {
      "i": 113,
      "t": 3.7666666666666666,
      "type_id": 0,
      "level_id": 2,
      "boundary_p": 0.12628178298473358
    },
    {
      "i": 114,
      "t": 3.8,
      "type_id": 0,
      "level_id": 3,
      "boundary_p": 0.3985447287559509
    },
    {
      "i": 115,
      "t": 3.8333333333333335,
      "type_id": 0,
      "level_id": 4,
      "boundary_p": 0.028168287128210068
    },
    {
      "i": 116,
      "t": 3.8666666666666667,
      "type_id": 0,
      "level_id": 3,
      "boundary_p": 0.020277319476008415
    },
    {
      "i": 117,
      "t": 3.9,
      "type_id": 0,
      "level_id": 4,
      "boundary_p": 0.0009091508109122515
    },
    {
      "i": 118,
      "t": 3.933333333333333,
      "type_id": 0,
      "level_id": 2,
      "boundary_p": 0.005608057603240013
    },
    {
      "i": 119,
      "t": 3.966666666666667,
      "type_id": 0,
      "level_id": 4,
      "boundary_p": 0.011461528949439526
    },
    {
      "i": 120,
      "t": 4.0,
      "type_id": 0,
      "level_id": 4,
      "boundary_p": 0.009839361533522606
    },
    {
      "i": 121,
      "t": 4.033333333333333,
      "type_id": 0,
      "level_id": 3,
      "boundary_p": 0.005315365735441446
    },
    {
      "i": 122,
      "t": 4.066666666666666,
      "type_id": 0,
      "level_id": 3,
      "boundary_p": 0.00811122078448534
    },
    {
      "i": 123,
      "t": 4.1,
      "type_id": 0,
      "level_id": 4,
      "boundary_p": 0.16650144755840302
    },
    {
      "i": 124,
      "t": 4.133333333333334,
      "type_id": 0,
      "level_id": 3,
      "boundary_p": 0.17673684656620026
    },
    {
      "i": 125,
      "t": 4.166666666666667,
      "type_id": 0,
      "level_id": 3,
      "boundary_p": 0.8988058567047119
    },
    {
      "i": 126,
      "t": 4.2,
      "type_id": 3,
      "level_id": 2,
      "boundary_p": 0.03751591220498085
    },
    {
      "i": 127,
      "t": 4.233333333333333,
      "type_id": 3,
      "level_id": 4,
      "boundary_p": 0.011124829761683941
    },
    {
      "i": 128,
      "t": 4.266666666666667,
      "type_id": 0,
      "level_id": 4,
      "boundary_p": 0.019478565081954002
    },
    {
      "i": 129,
      "t": 4.3,
      "type_id": 0,
      "level_id": 4,
      "boundary_p": 0.013894445262849331
    },
    {
      "i": 130,
      "t": 4.333333333333333,
      "type_id": 0,
      "level_id": 4,
      "boundary_p": 0.0017056469805538654
    },
    {
      "i": 131,
      "t": 4.366666666666666,
      "type_id": 0,
      "level_id": 2,
      "boundary_p": 0.0003668935678433627
    },
    {
      "i": 132,
      "t": 4.4,
      "type_id": 0,
      "level_id": 3,
      "boundary_p": 0.007543167099356651
    },
    {
      "i": 133,
      "t": 4.433333333333334,
      "type_id": 0,
      "level_id": 4,
      "boundary_p": 0.01444851141422987
    },
    {
      "i": 134,
      "t": 4.466666666666667,
      "type_id": 0,
      "level_id": 4,
      "boundary_p": 0.0864623561501503
    },
    {
      "i": 135,
      "t": 4.5,
      "type_id": 0,
      "level_id": 4,
      "boundary_p": 0.11902632564306259
    },
    {
      "i": 136,
      "t": 4.533333333333333,
      "type_id": 0,
      "level_id": 4,
      "boundary_p": 0.025473183020949364
    },
    {
      "i": 137,
      "t": 4.566666666666666,
      "type_id": 0,
      "level_id": 3,
      "boundary_p": 0.013040904887020588
    },
    {
      "i": 138,
      "t": 4.6,
      "type_id": 0,
      "level_id": 2,
      "boundary_p": 0.0007019595941528678
    },
    {
      "i": 139,
      "t": 4.633333333333334,
      "type_id": 0,
      "level_id": 3,
      "boundary_p": 0.003289090935140848
    },
    {
      "i": 140,
      "t": 4.666666666666667,
      "type_id": 0,
      "level_id": 3,
      "boundary_p": 0.008009606972336769
    },
    {
      "i": 141,
      "t": 4.7,
      "type_id": 0,
      "level_id": 4,
      "boundary_p": 0.0007434308063238859
    },
    {
      "i": 142,
      "t": 4.733333333333333,
      "type_id": 0,
      "level_id": 4,
      "boundary_p": 0.00014631098019890487
    },
    {
      "i": 143,
      "t": 4.766666666666667,
      "type_id": 0,
      "level_id": 3,
      "boundary_p": 0.00019826681818813086
    },
    {
      "i": 144,
      "t": 4.8,
      "type_id": 0,
      "level_id": 4,
      "boundary_p": 0.0009557597222737968
    },
    {
      "i": 145,
      "t": 4.833333333333333,
      "type_id": 0,
      "level_id": 4,
      "boundary_p": 0.04895695671439171
    },
    {
      "i": 146,
      "t": 4.866666666666666,
      "type_id": 1,
      "level_id": 3,
      "boundary_p": 0.010171261616051197
    },
    {
      "i": 147,
      "t": 4.9,
      "type_id": 1,
      "level_id": 3,
      "boundary_p": 0.00843870546668768
    },
    {
      "i": 148,
      "t": 4.933333333333334,
      "type_id": 0,
      "level_id": 3,
      "boundary_p": 0.007786145433783531
    },
    {
      "i": 149,
      "t": 4.966666666666667,
      "type_id": 0,
      "level_id": 3,
      "boundary_p": 0.04889366403222084
    },
    {
      "i": 150,
      "t": 5.0,
      "type_id": 3,
      "level_id": 3,
      "boundary_p": 0.027657635509967804
    },
    {
      "i": 151,
      "t": 5.033333333333333,
      "type_id": 0,
      "level_id": 3,
      "boundary_p": 0.22301633656024933
    },
    {
      "i": 152,
      "t": 5.066666666666666,
      "type_id": 0,
      "level_id": 3,
      "boundary_p": 0.7133179903030396
    },
    {
      "i": 153,
      "t": 5.1,
      "type_id": 0,
      "level_id": 3,
      "boundary_p": 0.8757782578468323
    },
    {
      "i": 154,
      "t": 5.133333333333334,
      "type_id": 0,
      "level_id": 3,
      "boundary_p": 0.1370103359222412
    },
    {
      "i": 155,
      "t": 5.166666666666667,
      "type_id": 0,
      "level_id": 3,
      "boundary_p": 0.00468362495303154
    },
    {
      "i": 156,
      "t": 5.2,
      "type_id": 0,
      "level_id": 3,
      "boundary_p": 0.001693903119303286
    },
    {
      "i": 157,
      "t": 5.233333333333333,
      "type_id": 0,
      "level_id": 3,
      "boundary_p": 0.0012191857676953077
    },
    {
      "i": 158,
      "t": 5.266666666666667,
      "type_id": 0,
      "level_id": 2,
      "boundary_p": 0.0031217040959745646
    },
    {
      "i": 159,
      "t": 5.3,
      "type_id": 0,
      "level_id": 2,
      "boundary_p": 0.008840730413794518
    },
    {
      "i": 160,
      "t": 5.333333333333333,
      "type_id": 0,
      "level_id": 3,
      "boundary_p": 0.09918559342622757
    },
    {
      "i": 161,
      "t": 5.366666666666666,
      "type_id": 0,
      "level_id": 3,
      "boundary_p": 0.12976017594337463
    },
    {
      "i": 162,
      "t": 5.4,
      "type_id": 0,
      "level_id": 3,
      "boundary_p": 0.034371379762887955
    },
    {
      "i": 163,
      "t": 5.433333333333334,
      "type_id": 1,
      "level_id": 3,
      "boundary_p": 0.003591612447053194
    },
    {
      "i": 164,
      "t": 5.466666666666667,
      "type_id": 0,
      "level_id": 3,
      "boundary_p": 0.00754897715523839
    },
    {
      "i": 165,
      "t": 5.5,
      "type_id": 0,
      "level_id": 3,
      "boundary_p": 0.013594663701951504
    },
    {
      "i": 166,
      "t": 5.533333333333333,
      "type_id": 0,
      "level_id": 3,
      "boundary_p": 0.009215550497174263
    },
    {
      "i": 167,
      "t": 5.566666666666666,
      "type_id": 0,
      "level_id": 3,
      "boundary_p": 0.013844357803463936
    },
    {
      "i": 168,
      "t": 5.6,
      "type_id": 0,
      "level_id": 3,
      "boundary_p": 0.005259714554995298
    },
    {
      "i": 169,
      "t": 5.633333333333334,
      "type_id": 0,
      "level_id": 3,
      "boundary_p": 0.0014949305914342403
    },
    {
      "i": 170,
      "t": 5.666666666666667,
      "type_id": 0,
      "level_id": 4,
      "boundary_p": 0.0013625530991703272
    },
    {
      "i": 171,
      "t": 5.7,
      "type_id": 0,
      "level_id": 2,
      "boundary_p": 0.0038166996091604233
    },
    {
      "i": 172,
      "t": 5.733333333333333,
      "type_id": 0,
      "level_id": 2,
      "boundary_p": 0.05407748743891716
    },
    {
      "i": 173,
      "t": 5.766666666666667,
      "type_id": 0,
      "level_id": 3,
      "boundary_p": 0.303295373916626
    },
    {
      "i": 174,
      "t": 5.8,
      "type_id": 0,
      "level_id": 2,
      "boundary_p": 0.1009986475110054
    },
    {
      "i": 175,
      "t": 5.833333333333333,
      "type_id": 0,
      "level_id": 3,
      "boundary_p": 0.04155248776078224
    },
    {
      "i": 176,
      "t": 5.866666666666666,
      "type_id": 0,
      "level_id": 4,
      "boundary_p": 0.9426791071891785
    },
    {
      "i": 177,
      "t": 5.9,
      "type_id": 0,
      "level_id": 3,
      "boundary_p": 0.5864854454994202
    },
    {
      "i": 178,
      "t": 5.933333333333334,
      "type_id": 1,
      "level_id": 2,
      "boundary_p": 0.00359283946454525
    },
    {
      "i": 179,
      "t": 5.966666666666667,
      "type_id": 0,
      "level_id": 3,
      "boundary_p": 0.0029499568045139313
    },
    {
      "i": 180,
      "t": 6.0,
      "type_id": 0,
      "level_id": 4,
      "boundary_p": 0.014007240533828735
    },
    {
      "i": 181,
      "t": 6.033333333333333,
      "type_id": 0,
      "level_id": 3,
      "boundary_p": 0.02490944415330887
    },
    {
      "i": 182,
      "t": 6.066666666666666,
      "type_id": 0,
      "level_id": 3,
      "boundary_p": 0.016368210315704346
    },
    {
      "i": 183,
      "t": 6.1,
      "type_id": 0,
      "level_id": 4,
      "boundary_p": 0.07783190160989761
    },
    {
      "i": 184,
      "t": 6.133333333333334,
      "type_id": 0,
      "level_id": 3,
      "boundary_p": 0.11331218481063843
    },
    {
      "i": 185,
      "t": 6.166666666666667,
      "type_id": 0,
      "level_id": 3,
      "boundary_p": 0.03099116124212742
    },
    {
      "i": 186,
      "t": 6.2,
      "type_id": 0,
      "level_id": 2,
      "boundary_p": 0.022716253995895386
    },
    {
      "i": 187,
      "t": 6.233333333333333,
      "type_id": 1,
      "level_id": 4,
      "boundary_p": 0.0808684229850769
    },
    {
      "i": 188,
      "t": 6.266666666666667,
      "type_id": 0,
      "level_id": 4,
      "boundary_p": 0.16134218871593475
    },
    {
      "i": 189,
      "t": 6.3,
      "type_id": 0,
      "level_id": 3,
      "boundary_p": 0.03316956013441086
    },
    {
      "i": 190,
      "t": 6.333333333333333,
      "type_id": 0,
      "level_id": 2,
      "boundary_p": 0.007191830314695835
    },
    {
      "i": 191,
      "t": 6.366666666666666,
      "type_id": 1,
      "level_id": 4,
      "boundary_p": 0.010112715885043144
    },
    {
      "i": 192,
      "t": 6.4,
      "type_id": 0,
      "level_id": 3,
      "boundary_p": 0.0015754160704091191
    },
    {
      "i": 193,
      "t": 6.433333333333334,
      "type_id": 0,
      "level_id": 3,
      "boundary_p": 0.0009489973890595138
    },
    {
      "i": 194,
      "t": 6.466666666666667,
      "type_id": 0,
      "level_id": 3,
      "boundary_p": 0.006234782747924328
    },
    {
      "i": 195,
      "t": 6.5,
      "type_id": 0,
      "level_id": 3,
      "boundary_p": 0.0008477224037051201
    },
    {
      "i": 196,
      "t": 6.533333333333333,
      "type_id": 0,
      "level_id": 3,
      "boundary_p": 0.0008657585713081062
    },
    {
      "i": 197,
      "t": 6.566666666666666,
      "type_id": 0,
      "level_id": 2,
      "boundary_p": 0.012535632587969303
    },
    {
      "i": 198,
      "t": 6.6,
      "type_id": 0,
      "level_id": 2,
      "boundary_p": 0.05469389259815216
    },
    {
      "i": 199,
      "t": 6.633333333333334,
      "type_id": 0,
      "level_id": 3,
      "boundary_p": 0.2783834934234619
    },
    {
      "i": 200,
      "t": 6.666666666666667,
      "type_id": 0,
      "level_id": 3,
      "boundary_p": 0.4737178087234497
    }
  ]
}