{
  "wav": "utt_0006.wav",
  "sample_rate": 16000,
  "fps": 30,
  "duration": 7.7635,
  "type_map": [
    "happy",
    "sad",
    "angry",
    "fear",
    "calm",
    "confused"
  ],
  "switch_params": {
    "thr_on": 0.78,
    "thr_off": 0.6,
    "confirm_win": 3,
    "min_gap": 5
  },
  "switch_frames": [
    45,
    94,
    99,
    132,
    189,
    194
  ],
  "switch_times": [
    1.5,
    3.1333333333333333,
    3.3,
    4.4,
    6.3,
    6.466666666666667
  ],
  "frames": [
    {
      "i": 0,
      "t": 0.0,
      "type_id": 3,
      "level_id": 5,
      "boundary_p": 0.0006989504327066243
    },
    {
      "i": 1,
      "t": 0.03333333333333333,
      "type_id": 3,
      "level_id": 3,
      "boundary_p": 0.001191424671560526
    },
    {
      "i": 2,
      "t": 0.06666666666666667,
      "type_id": 3,
      "level_id": 5,
      "boundary_p": 0.006128212437033653
    },
    {
      "i": 3,
      "t": 0.1,
      "type_id": 0,
      "level_id": 5,
      "boundary_p": 0.006592850666493177
    },
    {
      "i": 4,
      "t": 0.13333333333333333,
      "type_id": 1,
      "level_id": 2,
      "boundary_p": 0.09610442817211151
    },
    {
      "i": 5,
      "t": 0.16666666666666666,
      "type_id": 1,
      "level_id": 2,
      "boundary_p": 0.11670473963022232
    },
    {
      "i": 6,
      "t": 0.2,
      "type_id": 3,
      "level_id": 1,
      "boundary_p": 0.11809272319078445
    },
    {
      "i": 7,
      "t": 0.23333333333333334,
      "type_id": 3,
      "level_id": 2,
      "boundary_p": 0.06056094914674759
    },
    {
      "i": 8,
      "t": 0.26666666666666666,
      "type_id": 1,
      "level_id": 2,
      "boundary_p": 0.061440642923116684
    },
    {
      "i": 9,
      "t": 0.3,
      "type_id": 1,
      "level_id": 2,
      "boundary_p": 0.06133732199668884
    },
    {
      "i": 10,
      "t": 0.3333333333333333,
      "type_id": 1,
      "level_id": 1,
      "boundary_p": 0.025561431422829628
    },
    {
      "i": 11,
      "t": 0.36666666666666664,
      "type_id": 3,
      "level_id": 1,
      "boundary_p": 0.01671506091952324
    },
    {
      "i": 12,
      "t": 0.4,
      "type_id": 3,
      "level_id": 1,
      "boundary_p": 0.06139448285102844
    },
    {
      "i": 13,
      "t": 0.43333333333333335,
      "type_id": 1,
      "level_id": 5,
      "boundary_p": 0.018104394897818565
    },
    {
      "i": 14,
      "t": 0.4666666666666667,
      "type_id": 1,
      "level_id": 3,
      "boundary_p": 0.006108553614467382
    },
    {
      "i": 15,
      "t": 0.5,
      "type_id": 1,
      "level_id": 3,
      "boundary_p": 0.00036521797301247716
    },
    {
      "i": 16,
      "t": 0.5333333333333333,
      "type_id": 1,
      "level_id": 3,
      "boundary_p": 2.166152626159601e-05
    },
    {
      "i": 17,
      "t": 0.5666666666666667,
      "type_id": 1,
      "level_id": 3,
      "boundary_p": 1.1590407666517422e-05
    },
    {
      "i": 18,
      "t": 0.6,
      "type_id": 1,
      "level_id": 3,
      "boundary_p": 0.00011127288598800078
    },
    {
      "i": 19,
      "t": 0.6333333333333333,
      "type_id": 1,
      "level_id": 3,
      "boundary_p": 0.00010638644744176418
    },
    {
      "i": 20,
      "t": 0.6666666666666666,
      "type_id": 1,
      "level_id": 3,
      "boundary_p": 0.000591689720749855
    },
    {
      "i": 21,
      "t": 0.7,
      "type_id": 1,
      "level_id": 3,
      "boundary_p": 0.0334281362593174
    },
    {
      "i": 22,
      "t": 0.7333333333333333,
      "type_id": 1,
      "level_id": 3,
      "boundary_p": 0.1280505359172821
    },
    {
      "i": 23,
      "t": 0.7666666666666667,
      "type_id": 1,
      "level_id": 1,
      "boundary_p": 0.018206650391221046
    },
    {
      "i": 24,
      "t": 0.8,
      "type_id": 1,
      "level_id": 2,
      "boundary_p": 0.07205136865377426
    },
    {
      "i": 25,
      "t": 0.8333333333333334,
      "type_id": 1,
      "level_id": 3,
      "boundary_p": 0.16210079193115234
    },
    {
      "i": 26,
      "t": 0.8666666666666667,
      "type_id": 1,
      "level_id": 3,
      "boundary_p": 0.007968958467245102
    },
    {
      "i": 27,
      "t": 0.9,
      "type_id": 1,
      "level_id": 1,
      "boundary_p": 0.007324348669499159
    },
    {
      "i": 28,
      "t": 0.9333333333333333,
      "type_id": 1,
      "level_id": 5,
      "boundary_p": 0.007340011652559042
    },
    {
      "i": 29,
      "t": 0.9666666666666667,
      "type_id": 1,
      "level_id": 5,
      "boundary_p": 0.003108782460913062
    },
    {
      "i": 30,
      "t": 1.0,
      "type_id": 1,
      "level_id": 2,
      "boundary_p": 0.0009909453801810741
    },
    {
      "i": 31,
      "t": 1.0333333333333334,
      "type_id": 1,
      "level_id": 3,
      "boundary_p": 0.021932583302259445
    },
    {
      "i": 32,
      "t": 1.0666666666666667,
      "type_id": 1,
      "level_id": 3,
      "boundary_p": 0.00901440717279911
    },
    {
      "i": 33,
      "t": 1.1,
      "type_id": 1,
      "level_id": 3,
      "boundary_p": 0.05686008930206299
    },
    {
      "i": 34,
      "t": 1.1333333333333333,
      "type_id": 1,
      "level_id": 3,
      "boundary_p": 0.048654451966285706
    },
    {
      "i": 35,
      "t": 1.1666666666666667,
      "type_id": 3,
      "level_id": 3,
      "boundary_p": 0.01877516880631447
    },
    {
      "i": 36,
      "t": 1.2,
      "type_id": 1,
      "level_id": 4,
      "boundary_p": 0.0854717269539833
    },
    {
      "i": 37,
      "t": 1.2333333333333334,
      "type_id": 1,
      "level_id": 5,
      "boundary_p": 0.002473178319633007
    },
    {
      "i": 38,
      "t": 1.2666666666666666,
      "type_id": 1,
      "level_id": 4,
      "boundary_p": 0.0002674659772310406
    },
    {
      "i": 39,
      "t": 1.3,
      "type_id": 1,
      "level_id": 4,
      "boundary_p": 0.0018757586367428303
    },
    {
      "i": 40,
      "t": 1.3333333333333333,
      "type_id": 3,
      "level_id": 4,
      "boundary_p": 0.00021771933825220913
    },
    {
      "i": 41,
      "t": 1.3666666666666667,
      "type_id": 1,
      "level_id": 4,
      "boundary_p": 0.0008798538474366069
    },
    {
      "i": 42,
      "t": 1.4,
      "type_id": 3,
      "level_id": 4,
      "boundary_p": 0.2958531677722931
    },
    {
      "i": 43,
      "t": 1.4333333333333333,
      "type_id": 3,
      "level_id": 2,
      "boundary_p": 0.11452355980873108
    },
    {
      "i": 44,
      "t": 1.4666666666666666,
      "type_id": 3,
      "level_id": 3,
      "boundary_p": 0.16758838295936584
    },
    {
      "i": 45,
      "t": 1.5,
      "type_id": 0,
      "level_id": 3,
      "boundary_p": 0.8843550086021423
    },
    {
      "i": 46,
      "t": 1.5333333333333334,
      "type_id": 1,
      "level_id": 4,
      "boundary_p": 0.2816351652145386
    },
    {
      "i": 47,
      "t": 1.5666666666666667,
      "type_id": 0,
      "level_id": 3,
      "boundary_p": 0.2705204486846924
    },
    {
      "i": 48,
      "t": 1.6,
      "type_id": 3,
      "level_id": 3,
      "boundary_p": 0.21943554282188416
    },
    {
      "i": 49,
      "t": 1.6333333333333333,
      "type_id": 3,
      "level_id": 3,
      "boundary_p": 0.03198317065834999
    },
    {
      "i": 50,
      "t": 1.6666666666666667,
      "type_id": 3,
      "level_id": 4,
      "boundary_p": 0.07578622549772263
    },
    {
      "i": 51,
      "t": 1.7,
      "type_id": 3,
      "level_id": 3,
      "boundary_p": 0.03984272480010986
    },
    {
      "i": 52,
      "t": 1.7333333333333334,
      "type_id": 3,
      "level_id": 3,
      "boundary_p": 0.01166895404458046
    },
    {
      "i": 53,
      "t": 1.7666666666666666,
      "type_id": 3,
      "level_id": 5,
      "boundary_p": 0.001688623335212469
    },
    {
      "i": 54,
      "t": 1.8,
      "type_id": 3,
      "level_id": 5,
      "boundary_p": 0.0003282836696598679
    },
    {
      "i": 55,
      "t": 1.8333333333333333,
      "type_id": 3,
      "level_id": 5,
      "boundary_p": 0.00010309179924661294
    },
    {
      "i": 56,
      "t": 1.8666666666666667,
      "type_id": 3,
      "level_id": 3,
      "boundary_p": 3.4480286558391526e-05
    },
    {
      "i": 57,
      "t": 1.9,
      "type_id": 3,
      "level_id": 5,
      "boundary_p": 0.00012161771155660972
    },
    {
      "i": 58,
      "t": 1.9333333333333333,
      "type_id": 3,
      "level_id": 4,
      "boundary_p": 9.046989725902677e-05
    },
    {
      "i": 59,
      "t": 1.9666666666666666,
      "type_id": 3,
      "level_id": 3,
      "boundary_p": 8.461853576591238e-05
    },
    {
      "i": 60,
      "t": 2.0,
      "type_id": 3,
      "level_id": 4,
      "boundary_p": 0.005004772450774908
    },
    {
      "i": 61,
      "t": 2.033333333333333,
      "type_id": 3,
      "level_id": 4,
      "boundary_p": 0.2065715491771698
    },
    {
      "i": 62,
      "t": 2.066666666666667,
      "type_id": 3,
      "level_id": 5,
      "boundary_p": 0.12392441183328629
    },
    {
      "i": 63,
      "t": 2.1,
      "type_id": 3,
      "level_id": 3,
      "boundary_p": 0.015354834496974945
    },
    {
      "i": 64,
      "t": 2.1333333333333333,
      "type_id": 3,
      "level_id": 5,
      "boundary_p": 0.0049019367434084415
    },
    {
      "i": 65,
      "t": 2.1666666666666665,
      "type_id": 3,
      "level_id": 5,
      "boundary_p": 0.0029975920915603638
    },
    {
      "i": 66,
      "t": 2.2,
      "type_id": 3,
      "level_id": 4,
      "boundary_p": 0.03232090175151825
    },
    {
      "i": 67,
      "t": 2.2333333333333334,
      "type_id": 3,
      "level_id": 3,
      "boundary_p": 0.10451357066631317
    },
    {
      "i": 68,
      "t": 2.2666666666666666,
      "type_id": 3,
      "level_id": 3,
      "boundary_p": 0.018699591979384422
    },
    {
      "i": 69,
      "t": 2.3,
      "type_id": 3,
      "level_id": 3,
      "boundary_p": 0.004076399374753237
    },
    {
      "i": 70,
      "t": 2.3333333333333335,
      "type_id": 3,
      "level_id": 4,
      "boundary_p": 0.004089287016540766
    },
    {
      "i": 71,
      "t": 2.3666666666666667,
      "type_id": 0,
      "level_id": 4,
      "boundary_p": 0.002705795457586646
    },
    {
      "i": 72,
      "t": 2.4,
      "type_id": 3,
      "level_id": 4,
      "boundary_p": 0.0006822967552579939
    },
    {
      "i": 73,
      "t": 2.433333333333333,
      "type_id": 3,
      "level_id": 3,
      "boundary_p": 0.0001083086826838553
    },
    {
      "i": 74,
      "t": 2.466666666666667,
      "type_id": 0,
      "level_id": 3,
      "boundary_p": 0.0010428220266476274
    },
    {
      "i": 75,
      "t": 2.5,
      "type_id": 3,
      "level_id": 3,
      "boundary_p": 0.0010612942278385162
    },
    {
      "i": 76,
      "t": 2.533333333333333,
      "type_id": 1,
      "level_id": 3,
      "boundary_p": 0.0498676672577858
    },
    {
      "i": 77,
      "t": 2.566666666666667,
      "type_id": 1,
      "level_id": 3,
      "boundary_p": 0.15420062839984894
    },
    {
      "i": 78,
      "t": 2.6,
      "type_id": 1,
      "level_id": 3,
      "boundary_p": 0.011025086045265198
    },
    {
      "i": 79,
      "t": 2.6333333333333333,
      "type_id": 1,
      "level_id": 3,
      "boundary_p": 0.002744772471487522
    },
    {
      "i": 80,
      "t": 2.6666666666666665,
      "type_id": 1,
      "level_id": 3,
      "boundary_p": 0.0006656296318396926
    },
    {
      "i": 81,
      "t": 2.7,
      "type_id": 1,
      "level_id": 3,
      "boundary_p": 0.0005236559081822634
    },
    {
      "i": 82,
      "t": 2.7333333333333334,
      "type_id": 1,
      "level_id": 3,
      "boundary_p": 0.000309966504573822
    },
    {
      "i": 83,
      "t": 2.7666666666666666,
      "type_id": 3,
      "level_id": 3,
      "boundary_p": 0.0002620611048769206
    },
    {
      "i": 84,
      "t": 2.8,
      "type_id": 3,
      "level_id": 3,
      "boundary_p": 0.0006729345768690109
    },
    {
      "i": 85,
      "t": 2.8333333333333335,
      "type_id": 1,
      "level_id": 3,
      "boundary_p": 0.0014364797389134765
    },
    {
      "i": 86,
      "t": 2.8666666666666667,
      "type_id": 3,
      "level_id": 3,
      "boundary_p": 0.0021484973840415478
    },
    {
      "i": 87,
      "t": 2.9,
      "type_id": 3,
      "level_id": 3,
      "boundary_p": 0.0007248969050124288
    },
    {
      "i": 88,
      "t": 2.933333333333333,
      "type_id": 3,
      "level_id": 3,
      "boundary_p": 0.0015194164589047432
    },
    {
      "i": 89,
      "t": 2.966666666666667,
      "type_id": 1,
      "level_id": 3,
      "boundary_p": 0.006919794250279665
    },
    {
      "i": 90,
      "t": 3.0,
      "type_id": 0,
      "level_id": 3,
      "boundary_p": 0.05033620446920395
    },
    {
      "i": 91,
      "t": 3.033333333333333,
      "type_id": 0,
      "level_id": 2,
      "boundary_p": 0.6734214425086975
    },
    {
      "i": 92,
      "t": 3.066666666666667,
      "type_id": 0,
      "level_id": 2,
      "boundary_p": 0.7483054995536804
    },
    {
      "i": 93,
      "t": 3.1,
      "type_id": 3,
      "level_id": 3,
      "boundary_p": 0.6055129170417786
    },
    {
      "i": 94,
      "t": 3.1333333333333333,
      "type_id": 0,
      "level_id": 3,
      "boundary_p": 0.8939619064331055
    },
    {
      "i": 95,
      "t": 3.1666666666666665,
      "type_id": 0,
      "level_id": 2,
      "boundary_p": 0.7523706555366516
    },
    {
      "i": 96,
      "t": 3.2,
      "type_id": 0,
      "level_id": 2,
      "boundary_p": 0.5787276029586792
    },
    {
      "i": 97,
      "t": 3.2333333333333334,
      "type_id": 0,
      "level_id": 2,
      "boundary_p": 0.8665040135383606
    },
    {
      "i": 98,
      "t": 3.2666666666666666,
      "type_id": 0,
      "level_id": 2,
      "boundary_p": 0.8032868504524231
    },
    {
      "i": 99,
      "t": 3.3,
      "type_id": 0,
      "level_id": 2,
      "boundary_p": 0.9198339581489563
    },
    {
      "i": 100,
      "t": 3.3333333333333335,
      "type_id": 0,
      "level_id": 3,
      "boundary_p": 0.7797118425369263
    },
    {
      "i": 101,
      "t": 3.3666666666666667,
      "type_id": 1,
      "level_id": 3,
      "boundary_p": 0.08363155275583267
    },
    {
      "i": 102,
      "t": 3.4,
      "type_id": 3,
      "level_id": 2,
      "boundary_p": 0.0021980165038257837
    },
    {
      "i": 103,
      "t": 3.433333333333333,
      "type_id": 1,
      "level_id": 2,
      "boundary_p": 0.0009414863889105618
    },
    {
      "i": 104,
      "t": 3.466666666666667,
      "type_id": 1,
      "level_id": 2,
      "boundary_p": 0.002650668378919363
    },
    {
      "i": 105,
      "t": 3.5,
      "type_id": 1,
      "level_id": 2,
      "boundary_p": 0.0022675443906337023
    },
    {
      "i": 106,
      "t": 3.533333333333333,
      "type_id": 0,
      "level_id": 2,
      "boundary_p": 0.006152983754873276
    },
    {
      "i": 107,
      "t": 3.566666666666667,
      "type_id": 1,
      "level_id": 2,
      "boundary_p": 0.0008409346337430179
    },
    {
      "i": 108,
      "t": 3.6,
      "type_id": 1,
      "level_id": 2,
      "boundary_p": 0.0019470934057608247
    },
    {
      "i": 109,
      "t": 3.6333333333333333,
      "type_id": 1,
      "level_id": 2,
      "boundary_p": 0.0011781634530052543
    },
    {
      "i": 110,
      "t": 3.6666666666666665,
      "type_id": 0,
      "level_id": 2,
      "boundary_p": 0.005122285336256027
    },
    {
      "i": 111,
      "t": 3.7,
      "type_id": 0,
      "level_id": 2,
      "boundary_p": 0.002220019232481718
    },
    {
      "i": 112,
      "t": 3.7333333333333334,
      "type_id": 0,
      "level_id": 2,
      "boundary_p": 0.029933756217360497
    },
    {
      "i": 113,
      "t": 3.7666666666666666,
      "type_id": 3,
      "level_id": 3,
      "boundary_p": 0.01482953131198883
    },
    {
      "i": 114,
      "t": 3.8,
      "type_id": 0,
      "level_id": 2,
      "boundary_p": 0.01122661866247654
    },
    {
      "i": 115,
      "t": 3.8333333333333335,
      "type_id": 0,
      "level_id": 2,
      "boundary_p": 0.004544635768979788
    },
    {
      "i": 116,
      "t": 3.8666666666666667,
      "type_id": 0,
      "level_id": 2,
      "boundary_p": 0.0006936619756743312
    },
    {
      "i": 117,
      "t": 3.9,
      "type_id": 1,
      "level_id": 2,
      "boundary_p": 0.0018607970559969544
    },
    {
      "i": 118,
      "t": 3.933333333333333,
      "type_id": 0,
      "level_id": 2,
      "boundary_p": 0.0034300864208489656
    },
    {
      "i": 119,
      "t": 3.966666666666667,
      "type_id": 1,
      "level_id": 2,
      "boundary_p": 0.003505501663312316
    },
    {
      "i": 120,
      "t": 4.0,
      "type_id": 0,
      "level_id": 2,
      "boundary_p": 0.012377050705254078
    },
    {
      "i": 121,
      "t": 4.033333333333333,
      "type_id": 0,
      "level_id": 2,
      "boundary_p": 0.023296887055039406
    },
    {
      "i": 122,
      "t": 4.066666666666666,
      "type_id": 0,
      "level_id": 2,
      "boundary_p": 0.02525070495903492
    },
    {
      "i": 123,
      "t": 4.1,
      "type_id": 0,
      "level_id": 4,
      "boundary_p": 0.21498385071754456
    },
    {
      "i": 124,
      "t": 4.133333333333334,
      "type_id": 1,
      "level_id": 2,
      "boundary_p": 0.012429684400558472
    },
    {
      "i": 125,
      "t": 4.166666666666667,
      "type_id": 0,
      "level_id": 4,
      "boundary_p": 0.0030445957090705633
    },
    {
      "i": 126,
      "t": 4.2,
      "type_id": 0,
      "level_id": 4,
      "boundary_p": 0.05572836473584175
    },
    {
      "i": 127,
      "t": 4.233333333333333,
      "type_id": 0,
      "level_id": 2,
      "boundary_p": 0.023046044632792473
    },
    {
      "i": 128,
      "t": 4.266666666666667,
      "type_id": 0,
      "level_id": 4,
      "boundary_p": 0.2088867723941803
    },
    {
      "i": 129,
      "t": 4.3,
      "type_id": 0,
      "level_id": 4,
      "boundary_p": 0.016642151400446892
    },
    {
      "i": 130,
      "t": 4.333333333333333,
      "type_id": 0,
      "level_id": 4,
      "boundary_p": 0.04198215901851654
    },
    {
      "i": 131,
      "t": 4.366666666666666,
      "type_id": 0,
      "level_id": 2,
      "boundary_p": 0.08190131932497025
    },
    {
      "i": 132,
      "t": 4.4,
      "type_id": 0,
      "level_id": 2,
      "boundary_p": 0.8537886738777161
    },
    {
      "i": 133,
      "t": 4.433333333333334,
      "type_id": 0,
      "level_id": 2,
      "boundary_p": 0.17210353910923004
    },
    {
      "i": 134,
      "t": 4.466666666666667,
      "type_id": 0,
      "level_id": 2,
      "boundary_p": 0.002906544366851449
    },
    {
      "i": 135,
      "t": 4.5,
      "type_id": 0,
      "level_id": 2,
      "boundary_p": 0.00026047462597489357
    },
    {
      "i": 136,
      "t": 4.533333333333333,
      "type_id": 0,
      "level_id": 4,
      "boundary_p": 0.02388756349682808
    },
    {
      "i": 137,
      "t": 4.566666666666666,
      "type_id": 0,
      "level_id": 4,
      "boundary_p": 0.08104398101568222
    },
    {
      "i": 138,
      "t": 4.6,
      "type_id": 0,
      "level_id": 4,
      "boundary_p": 0.07221504300832748
    },
    {
      "i": 139,
      "t": 4.633333333333334,
      "type_id": 1,
      "level_id": 4,
      "boundary_p": 0.016326338052749634
    },
    {
      "i": 140,
      "t": 4.666666666666667,
      "type_id": 0,
      "level_id": 4,
      "boundary_p": 0.1641041487455368
    },
    {
      "i": 141,
      "t": 4.7,
      "type_id": 1,
      "level_id": 4,
      "boundary_p": 0.06412225216627121
    },
    {
      "i": 142,
      "t": 4.733333333333333,
      "type_id": 0,
      "level_id": 3,
      "boundary_p": 0.03761762008070946
    },
    {
      "i": 143,
      "t": 4.766666666666667,
      "type_id": 0,
      "level_id": 4,
      "boundary_p": 0.1442733108997345
    },
    {
      "i": 144,
      "t": 4.8,
      "type_id": 3,
      "level_id": 4,
      "boundary_p": 0.007377136964350939
    },
    {
      "i": 145,
      "t": 4.833333333333333,
      "type_id": 3,
      "level_id": 4,
      "boundary_p": 0.005936365108937025
    },
    {
      "i": 146,
      "t": 4.866666666666666,
      "type_id": 0,
      "level_id": 4,
      "boundary_p": 0.0017979958793148398
    },
    {
      "i": 147,
      "t": 4.9,
      "type_id": 3,
      "level_id": 4,
      "boundary_p": 0.001932445797137916
    },
    {
      "i": 148,
      "t": 4.933333333333334,
      "type_id": 0,
      "level_id": 4,
      "boundary_p": 0.00038610980845987797
    },
    {
      "i": 149,
      "t": 4.966666666666667,
      "type_id": 0,
      "level_id": 4,
      "boundary_p": 0.000702324032317847
    },
    {
      "i": 150,
      "t": 5.0,
      "type_id": 0,
      "level_id": 4,
      "boundary_p": 0.07988394796848297
    },
    {
      "i": 151,
      "t": 5.033333333333333,
      "type_id": 0,
      "level_id": 4,
      "boundary_p": 0.05216347053647041
    },
    {
      "i": 152,
      "t": 5.066666666666666,
      "type_id": 0,
      "level_id": 4,
      "boundary_p": 0.1286417841911316
    },
    {
      "i": 153,
      "t": 5.1,
      "type_id": 1,
      "level_id": 4,
      "boundary_p": 0.024098441004753113
    },
    {
      "i": 154,
      "t": 5.133333333333334,
      "type_id": 3,
      "level_id": 4,
      "boundary_p": 0.005053283646702766
    },
    {
      "i": 155,
      "t": 5.166666666666667,
      "type_id": 3,
      "level_id": 4,
      "boundary_p": 0.03474792093038559
    },
    {
      "i": 156,
      "t": 5.2,
      "type_id": 3,
      "level_id": 4,
      "boundary_p": 0.0010787340579554439
    },
    {
      "i": 157,
      "t": 5.233333333333333,
      "type_id": 0,
      "level_id": 2,
      "boundary_p": 0.018204158172011375
    },
    {
      "i": 158,
      "t": 5.266666666666667,
      "type_id": 0,
      "level_id": 3,
      "boundary_p": 0.06860365718603134
    },
    {
      "i": 159,
      "t": 5.3,
      "type_id": 0,
      "level_id": 4,
      "boundary_p": 0.003466906026005745
    },
    {
      "i": 160,
      "t": 5.333333333333333,
      "type_id": 0,
      "level_id": 4,
      "boundary_p": 0.007211365271359682
    },
    {
      "i": 161,
      "t": 5.366666666666666,
      "type_id": 3,
      "level_id": 4,
      "boundary_p": 0.014317811466753483
    },
    {
      "i": 162,
      "t": 5.4,
      "type_id": 3,
      "level_id": 4,
      "boundary_p": 0.052469827234745026
    },
    {
      "i": 163,
      "t": 5.433333333333334,
      "type_id": 0,
      "level_id": 3,
      "boundary_p": 0.05136460065841675
    },
    {
      "i": 164,
      "t": 5.466666666666667,
      "type_id": 0,
      "level_id": 3,
      "boundary_p": 0.09371773153543472
    },
    {
      "i": 165,
      "t": 5.5,
      "type_id": 1,
      "level_id": 3,
      "boundary_p": 0.03387170657515526
    },
    {
      "i": 166,
      "t": 5.533333333333333,
      "type_id": 3,
      "level_id": 3,
      "boundary_p": 0.016802087426185608
    },
    {
      "i": 167,
      "t": 5.566666666666666,
      "type_id": 0,
      "level_id": 4,
      "boundary_p": 0.04146464914083481
    },
    {
      "i": 168,
      "t": 5.6,
      "type_id": 0,
      "level_id": 4,
      "boundary_p": 0.015034711919724941
    },
    {
      "i": 169,
      "t": 5.633333333333334,
      "type_id": 0,
      "level_id": 2,
      "boundary_p": 0.021438132971525192
    },
    {
      "i": 170,
      "t": 5.666666666666667,
      "type_id": 0,
      "level_id": 2,
      "boundary_p": 0.07360216975212097
    },
    {
      "i": 171,
      "t": 5.7,
      "type_id": 0,
      "level_id": 2,
      "boundary_p": 0.007739001419395208
    },
    {
      "i": 172,
      "t": 5.733333333333333,
      "type_id": 0,
      "level_id": 2,
      "boundary_p": 0.005725268740206957
    },
    {
      "i": 173,
      "t": 5.766666666666667,
      "type_id": 3,
      "level_id": 2,
      "boundary_p": 0.011529159732162952
    },
    {
      "i": 174,
      "t": 5.8,
      "type_id": 3,
      "level_id": 3,
      "boundary_p": 0.004704472608864307
    },
    {
      "i": 175,
      "t": 5.833333333333333,
      "type_id": 3,
      "level_id": 3,
      "boundary_p": 0.016616856679320335
    },
    {
      "i": 176,
      "t": 5.866666666666666,
      "type_id": 3,
      "level_id": 3,
      "boundary_p": 0.008218946866691113
    },
    {
      "i": 177,
      "t": 5.9,
      "type_id": 3,
      "level_id": 3,
      "boundary_p": 0.0017369277775287628
    },
    {
      "i": 178,
      "t": 5.933333333333334,
      "type_id": 0,
      "level_id": 3,
      "boundary_p": 0.000609084905590862
    },
    {
      "i": 179,
      "t": 5.966666666666667,
      "type_id": 3,
      "level_id": 3,
      "boundary_p": 0.017466289922595024
    },
    {
      "i": 180,
      "t": 6.0,
      "type_id": 0,
      "level_id": 2,
      "boundary_p": 0.13609136641025543
    },
    {
      "i": 181,
      "t": 6.033333333333333,
      "type_id": 0,
      "level_id": 2,
      "boundary_p": 0.001944739487953484
    },
    {
      "i": 182,
      "t": 6.066666666666666,
      "type_id": 0,
      "level_id": 4,
      "boundary_p": 0.019636347889900208
    },
    {
      "i": 183,
      "t": 6.1,
      "type_id": 0,
      "level_id": 3,
      "boundary_p": 0.07656710594892502
    },
    {
      "i": 184,
      "t": 6.133333333333334,
      "type_id": 0,
      "level_id": 2,
      "boundary_p": 0.027630353346467018
    },
    {
      "i": 185,
      "t": 6.166666666666667,
      "type_id": 0,
      "level_id": 3,
      "boundary_p": 0.013656212948262691
    },
    {
      "i": 186,
      "t": 6.2,
      "type_id": 0,
      "level_id": 2,
      "boundary_p": 0.08190497756004333
    },
    {
      "i": 187,
      "t": 6.233333333333333,
      "type_id": 0,
      "level_id": 2,
      "boundary_p": 0.03278600424528122
    },
    {
      "i": 188,
      "t": 6.266666666666667,
      "type_id": 0,
      "level_id": 2,
      "boundary_p": 0.09621372073888779
    },
    {
      "i": 189,
      "t": 6.3,
      "type_id": 0,
      "level_id": 2,
      "boundary_p": 0.8733946681022644
    },
    {
      "i": 190,
      "t": 6.333333333333333,
      "type_id": 3,
      "level_id": 4,
      "boundary_p": 0.23856733739376068
    },
    {
      "i": 191,
      "t": 6.366666666666666,
      "type_id": 0,
      "level_id": 2,
      "boundary_p": 0.20568671822547913
    },
    {
      "i": 192,
      "t": 6.4,
      "type_id": 0,
      "level_id": 3,
      "boundary_p": 0.4800114929676056
    },
    {
      "i": 193,
      "t": 6.433333333333334,
      "type_id": 0,
      "level_id": 2,
      "boundary_p": 0.9688754677772522
    },
    {
      "i": 194,
      "t": 6.466666666666667,
      "type_id": 0,
      "level_id": 2,
      "boundary_p": 0.8915205001831055
    },
    {
      "i": 195,
      "t": 6.5,
      "type_id": 0,
      "level_id": 3,
      "boundary_p": 0.30657556653022766
    },
    {
      "i": 196,
      "t": 6.533333333333333,
      "type_id": 0,
      "level_id": 2,
      "boundary_p": 0.1405808925628662
    },
    {
      "i": 197,
      "t": 6.566666666666666,
      "type_id": 0,
      "level_id": 2,
      "boundary_p": 0.03347551450133324
    },
    {
      "i": 198,
      "t": 6.6,
      "type_id": 1,
      "level_id": 2,
      "boundary_p": 0.0066064270213246346
    },
    {
      "i": 199,
      "t": 6.633333333333334,
      "type_id": 1,
      "level_id": 2,
      "boundary_p": 0.003763536224141717
    },
    {
      "i": 200,
      "t": 6.666666666666667,
      "type_id": 1,
      "level_id": 3,
      "boundary_p": 0.0001693613303359598
    },
    {
      "i": 201,
      "t": 6.7,
      "type_id": 1,
      "level_id": 3,
      "boundary_p": 0.0064745075069367886
    },
    {
      "i": 202,
      "t": 6.733333333333333,
      "type_id": 0,
      "level_id": 3,
      "boundary_p": 0.008021872490644455
    },
    {
      "i": 203,
      "t": 6.766666666666667,
      "type_id": 2,
      "level_id": 3,
      "boundary_p": 0.003045124001801014
    },
    {
      "i": 204,
      "t": 6.8,
      "type_id": 0,
      "level_id": 3,
      "boundary_p": 0.006532524712383747
    },
    {
      "i": 205,
      "t": 6.833333333333333,
      "type_id": 1,
      "level_id": 3,
      "boundary_p": 0.000948574801441282
    },
    {
      "i": 206,
      "t": 6.866666666666666,
      "type_id": 0,
      "level_id": 3,
      "boundary_p": 0.0011014190968126059
    },
    {
      "i": 207,
      "t": 6.9,
      "type_id": 1,
      "level_id": 3,
      "boundary_p": 0.00017301113985013217
    },
    {
      "i": 208,
      "t": 6.933333333333334,
      "type_id": 0,
      "level_id": 3,
      "boundary_p": 0.0005471005570143461
    },
    {
      "i": 209,
      "t": 6.966666666666667,
      "type_id": 0,
      "level_id": 3,
      "boundary_p": 0.0050232610665261745
    },
    {
      "i": 210,
      "t": 7.0,
      "type_id": 0,
      "level_id": 4,
      "boundary_p": 0.003081255592405796
    },
    {
      "i": 211,
      "t": 7.033333333333333,
      "type_id": 0,
      "level_id": 3,
      "boundary_p": 0.009073990397155285
    },
    {
      "i": 212,
      "t": 7.066666666666666,
      "type_id": 0,
      "level_id": 3,
      "boundary_p": 0.011459567584097385
    },
    {
      "i": 213,
      "t": 7.1,
      "type_id": 0,
      "level_id": 4,
      "boundary_p": 0.01053518895059824
    },
    {
      "i": 214,
      "t": 7.133333333333334,
      "type_id": 0,
      "level_id": 4,
      "boundary_p": 0.008947785012423992
    },
    {
      "i": 215,
      "t": 7.166666666666667,
      "type_id": 1,
      "level_id": 4,
      "boundary_p": 0.040305882692337036
    },
    {
      "i": 216,
      "t": 7.2,
      "type_id": 1,
      "level_id": 3,
      "boundary_p": 0.05822090804576874
    },
    {
      "i": 217,
      "t": 7.233333333333333,
      "type_id": 1,
      "level_id": 3,
      "boundary_p": 0.0068513620644807816
    },
    {
      "i": 218,
      "t": 7.266666666666667,
      "type_id": 0,
      "level_id": 3,
      "boundary_p": 0.007875838316977024
    },
    {
      "i": 219,
      "t": 7.3,
      "type_id": 3,
      "level_id": 3,
      "boundary_p": 0.012800649739801884
    },
    {
      "i": 220,
      "t": 7.333333333333333,
      "type_id": 0,
      "level_id": 4,
      "boundary_p": 0.008195929229259491
    },
    {
      "i": 221,
      "t": 7.366666666666666,
      "type_id": 0,
      "level_id": 4,
      "boundary_p": 0.0017403041711077094
    },
    {
      "i": 222,
      "t": 7.4,
      "type_id": 1,
      "level_id": 4,
      "boundary_p": 0.0006285640993155539
    },
    {
      "i": 223,
      "t": 7.433333333333334,
      "type_id": 1,
      "level_id": 3,
      "boundary_p": 0.0010762745514512062
    },
    {
      "i": 224,
      "t": 7.466666666666667,
      "type_id": 1,
      "level_id": 3,
      "boundary_p": 0.005138933192938566
    },
    {
      "i": 225,
      "t": 7.5,
      "type_id": 1,
      "level_id": 3,
      "boundary_p": 0.0678367093205452
    },
    {
      "i": 226,
      "t": 7.533333333333333,
      "type_id": 1,
      "level_id": 3,
      "boundary_p": 0.016739293932914734
    },
    {
      "i": 227,
      "t": 7.566666666666666,
      "type_id": 1,
      "level_id": 3,
      "boundary_p": 0.013865591026842594
    },
    {
      "i": 228,
      "t": 7.6,
      "type_id": 0,
      "level_id": 3,
      "boundary_p": 0.017454566434025764
    },
    {
      "i": 229,
      "t": 7.633333333333334,
      "type_id": 0,
      "level_id": 2,
      "boundary_p": 0.07293826341629028
    },
    {
      "i": 230,
      "t": 7.666666666666667,
      "type_id": 0,
      "level_id": 3,
      "boundary_p": 0.021382469683885574
    },
    {
      "i": 231,
      "t": 7.7,
      "type_id": 1,
      "level_id": 3,
      "boundary_p": 0.02721516415476799
    }
  ]
}